powernap/__init__.py
powernap/py.typed
powernap-2.0.0.dist-info/METADATA
powernap-2.0.0.dist-info/WHEEL
powernap-2.0.0.dist-info/licenses/LICENSE.md
powernap-2.0.0.dist-info/RECORD
