Metadata-Version: 2.4
Name: powernap
Version: 2.0.0
Summary: A small REST client that refills your batteries
Project-URL: Repository, https://github.com/ewjoachim/powernap
Author-email: Joachim Jablon <ewjoachim@gmail.com>
License: MIT License
License-File: LICENSE.md
Keywords: httpx,rest
Classifier: Development Status :: 4 - Beta
Classifier: Intended Audience :: Developers
Classifier: License :: OSI Approved :: MIT License
Classifier: Programming Language :: Python :: 3
Classifier: Programming Language :: Python :: 3.9
Classifier: Programming Language :: Python :: 3.10
Classifier: Programming Language :: Python :: 3.11
Classifier: Programming Language :: Python :: 3.12
Classifier: Programming Language :: Python :: 3.13
Requires-Python: >=3.9
Requires-Dist: httpx
Requires-Dist: typing-extensions
